moodsmith/__init__.py
moodsmith/cli.py
moodsmith/core.py
moodsmith/locales.py
moodsmith-1.0.2.dist-info/licenses/LICENSE
moodsmith-1.0.2.dist-info/METADATA
moodsmith-1.0.2.dist-info/WHEEL
moodsmith-1.0.2.dist-info/entry_points.txt
moodsmith-1.0.2.dist-info/top_level.txt
moodsmith-1.0.2.dist-info/RECORD
