Metadata-Version: 2.4
Name: moodsmith
Version: 1.0.2
Summary: A package designed to motivate you while you work, directly in your terminal.
Author-email: Samuel Yang <sy3638@nyu.edu>, Conor Tiernan <ct3551@nyu.edu>, Ganling Zhou <gz2184@nyu.edu>, Harrison Coon <hoc2006@nyu.edu>, Eason Huang <mh6455@nyu.edu>
License:                     GNU GENERAL PUBLIC LICENSE
Project-URL: Homepage, https://github.com/orgs/swe-students-fall2025/teams/team_harbor
Project-URL: Repository, https://github.com/orgs/swe-students-fall2025/teams/team_harbor.git
Keywords: python,package,productivity,motivation,focus,cli,terminal
Classifier: Programming Language :: Python :: 3
Classifier: Intended Audience :: Education
Classifier: License :: OSI Approved :: GNU General Public License v3 (GPLv3)
Classifier: Operating System :: OS Independent
Requires-Python: >=3.12
License-File: LICENSE
Provides-Extra: dev
Requires-Dist: pytest; extra == "dev"
Requires-Dist: pylint; extra == "dev"
Requires-Dist: build; extra == "dev"
Requires-Dist: twine; extra == "dev"
Dynamic: license-file
